hatch_docstring_description/__init__.py
hatch_docstring_description/hooks.py
hatch_docstring_description/py.typed
hatch_docstring_description/read_description.py
hatch_docstring_description-1.1.1.dist-info/METADATA
hatch_docstring_description-1.1.1.dist-info/WHEEL
hatch_docstring_description-1.1.1.dist-info/entry_points.txt
hatch_docstring_description-1.1.1.dist-info/licenses/LICENSE.md
hatch_docstring_description-1.1.1.dist-info/RECORD
