Metadata-Version: 2.4
Name: hatch-docstring-description
Version: 1.1.1
Summary: A hatchling plugin to read the description from the package docstring
Project-URL: Issues, https://github.com/flying-sheep/hatch-docstring-description/issues
Project-URL: Source, https://github.com/flying-sheep/hatch-docstring-description
Author-email: "Philipp A." <flying-sheep@web.de>
License-Expression: GPL-3.0-or-later
License-File: LICENSE.md
Classifier: Development Status :: 5 - Production/Stable
Classifier: Framework :: Hatch
Classifier: Programming Language :: Python
Classifier: Programming Language :: Python :: 3 :: Only
Classifier: Programming Language :: Python :: 3.9
Classifier: Programming Language :: Python :: 3.10
Classifier: Programming Language :: Python :: 3.11
Classifier: Programming Language :: Python :: 3.12
Classifier: Programming Language :: Python :: 3.13
Classifier: Typing :: Typed
Requires-Python: >=3.9
Requires-Dist: hatchling
